dasf_broker/__init__.py
dasf_broker/_version.py
dasf_broker/admin.py
dasf_broker/app_settings.py
dasf_broker/apps.py
dasf_broker/constants.py
dasf_broker/consumers.py
dasf_broker/logging.py
dasf_broker/models.py
dasf_broker/py.typed
dasf_broker/routing.py
dasf_broker/token_auth_middleware.py
dasf_broker/urls.py
dasf_broker/views.py
dasf_broker/frontend/__init__.py
dasf_broker/frontend/admin.py
dasf_broker/frontend/apps.py
dasf_broker/frontend/models.py
dasf_broker/frontend/urls.py
dasf_broker/frontend/views.py
dasf_broker/frontend/migrations/__init__.py
dasf_broker/frontend/static/dasf_frontend/dasf-web-component/README.md
dasf_broker/frontend/static/dasf_frontend/dasf-web-component/package.json
dasf_broker/frontend/static/dasf_frontend/dasf-web-component/LICENSES/Apache-2.0.txt
dasf_broker/frontend/static/dasf_frontend/dasf-web-component/LICENSES/CC-BY-4.0.txt
dasf_broker/frontend/static/dasf_frontend/dasf-web-component/LICENSES/CC0-1.0.txt
dasf_broker/frontend/static/dasf_frontend/dasf-web-component/dist/dasf.d.ts
dasf_broker/frontend/static/dasf_frontend/dasf-web-component/dist/dasf.js
dasf_broker/frontend/static/dasf_frontend/dasf-web-component/dist/dasf.umd.cjs
dasf_broker/frontend/static/dasf_frontend/dasf-web-component/dist/wc/dasf.d.ts
dasf_broker/frontend/static/dasf_frontend/dasf-web-component/dist/wc/dasf.js
dasf_broker/frontend/static/dasf_frontend/dasf-web-component/dist/wc/dasf.umd.cjs
dasf_broker/frontend/static/dasf_frontend/dasf-web-component/src/main.tsx
dasf_broker/frontend/static/dasf_frontend/dasf-web-component/src/vite-env.d.ts
dasf_broker/frontend/static/dasf_frontend/dasf-web-component/src/webcomponents.ts
dasf_broker/frontend/static/dasf_frontend/dasf-web-component/src/components/ClassContainer.tsx
dasf_broker/frontend/static/dasf_frontend/dasf-web-component/src/components/FunctionContainer.tsx
dasf_broker/frontend/static/dasf_frontend/dasf-web-component/src/components/FunctionForm.tsx
dasf_broker_django-0.0.1.dev1.dist-info/licenses/LICENSES/Apache-2.0.txt
dasf_broker_django-0.0.1.dev1.dist-info/licenses/LICENSES/CC-BY-4.0.txt
dasf_broker_django-0.0.1.dev1.dist-info/licenses/LICENSES/CC0-1.0.txt
dasf_broker_django-0.0.1.dev1.dist-info/licenses/LICENSES/EUPL-1.2.txt
dasf_broker_django-0.0.1.dev1.dist-info/METADATA
dasf_broker_django-0.0.1.dev1.dist-info/WHEEL
dasf_broker_django-0.0.1.dev1.dist-info/entry_points.txt
dasf_broker_django-0.0.1.dev1.dist-info/top_level.txt
dasf_broker_django-0.0.1.dev1.dist-info/RECORD
