Metadata-Version: 2.4
Name: dasf-broker-django
Version: 0.0.1.dev1
Summary: A message broker implementing the necessary protocoll for DASF, inspired by Apache Pulsar.
Author-email: "Philipp S. Sommer" <philipp.sommer@hereon.de>
Maintainer-email: "Philipp S. Sommer" <philipp.sommer@hereon.de>
License-Expression: EUPL-1.2
Project-URL: Homepage, https://codebase.helmholtz.cloud/dasf/dasf-broker-django
Project-URL: Documentation, https://dasf.readthedocs.io/projects/message-broker/en/latest/
Project-URL: Source, https://codebase.helmholtz.cloud/dasf/dasf-broker-django
Project-URL: Tracker, https://codebase.helmholtz.cloud/dasf/dasf-broker-django/issues/
Keywords: digital earth,helmholtz,gfz,potsdam,dasf,data analytics,django,messaging,rpc
Classifier: Intended Audience :: Developers
Classifier: Operating System :: OS Independent
Classifier: Programming Language :: Python
Classifier: Programming Language :: Python :: 3
Classifier: Programming Language :: Python :: 3 :: Only
Classifier: Programming Language :: Python :: 3.9
Classifier: Programming Language :: Python :: 3.10
Classifier: Programming Language :: Python :: 3.11
Classifier: Programming Language :: Python :: 3.12
Classifier: Programming Language :: Python :: 3.13
Classifier: Programming Language :: Python :: 3.14
Classifier: Typing :: Typed
Requires-Python: >=3.9
License-File: LICENSES/Apache-2.0.txt
License-File: LICENSES/CC-BY-4.0.txt
License-File: LICENSES/CC0-1.0.txt
License-File: LICENSES/EUPL-1.2.txt
Requires-Dist: Django<5.3,>=3.2
Requires-Dist: channels
Requires-Dist: django-guardian
Provides-Extra: pytest
Requires-Dist: pytest-django; extra == "pytest"
Requires-Dist: daphne; extra == "pytest"
Provides-Extra: testsite
Requires-Dist: dasf-broker-django[pytest]; extra == "testsite"
Requires-Dist: tox; extra == "testsite"
Requires-Dist: isort==7.0.0; extra == "testsite"
Requires-Dist: black==25.9.0; extra == "testsite"
Requires-Dist: blackdoc==0.4.5; extra == "testsite"
Requires-Dist: flake8==7.3.0; extra == "testsite"
Requires-Dist: pre-commit; extra == "testsite"
Requires-Dist: mypy==1.18.2; extra == "testsite"
Requires-Dist: pytest-cov; extra == "testsite"
Requires-Dist: reuse==6.1.2; extra == "testsite"
Requires-Dist: cffconvert; extra == "testsite"
Requires-Dist: django-environ; extra == "testsite"
Requires-Dist: django-stubs; extra == "testsite"
Requires-Dist: pytest-django; extra == "testsite"
Requires-Dist: demessaging; extra == "testsite"
Requires-Dist: djangorestframework; extra == "testsite"
Provides-Extra: docs
Requires-Dist: autodocsumm; extra == "docs"
Requires-Dist: sphinx-rtd-theme; extra == "docs"
Requires-Dist: hereon-netcdf-sphinxext; extra == "docs"
Requires-Dist: sphinx-design; extra == "docs"
Requires-Dist: django-environ; extra == "docs"
Requires-Dist: myst_parser; extra == "docs"
Requires-Dist: daphne; extra == "docs"
Requires-Dist: djangorestframework; extra == "docs"
Provides-Extra: dev
Requires-Dist: dasf-broker-django[testsite]; extra == "dev"
Requires-Dist: dasf-broker-django[docs]; extra == "dev"
Requires-Dist: reuse-shortcuts>=1.0.1; extra == "dev"
Requires-Dist: PyYAML; extra == "dev"
Requires-Dist: types-PyYAML; extra == "dev"
Dynamic: license-file
